pwh_permissions/__init__.py
pwh_permissions/pyramid.py
pwh_permissions-1.3.0.dist-info/LICENSE
pwh_permissions-1.3.0.dist-info/WHEEL
pwh_permissions-1.3.0.dist-info/METADATA
pwh_permissions-1.3.0.dist-info/RECORD
