Metadata-Version: 2.1
Name: pwh-permissions
Version: 1.3.0
Summary: A simple permissions parsing library for Python
License: MIT
Author: Mark Hall
Author-email: mark.hall@work.room3b.eu
Requires-Python: >=3.7,<4.0
Classifier: License :: OSI Approved :: MIT License
Classifier: Programming Language :: Python :: 3
Classifier: Programming Language :: Python :: 3.7
Classifier: Programming Language :: Python :: 3.8
Provides-Extra: pyramid
